olx_scraper/__init__.py
olx_scraper/analyzer.py
olx_scraper/scraper.py
olx_scraper/utils.py
olx_scraper_test-0.0.2.dist-info/METADATA
olx_scraper_test-0.0.2.dist-info/WHEEL
olx_scraper_test-0.0.2.dist-info/RECORD
