Metadata-Version: 2.1
Name: olx-scraper-test
Version: 0.0.2
Summary: Scrape olx for ad listings
License: MIT
Author: Akash NP
Author-email: akashnp1998@gmail.com
Requires-Python: >=3.8,<4.0
Classifier: License :: OSI Approved :: MIT License
Classifier: Programming Language :: Python :: 3
Classifier: Programming Language :: Python :: 3.8
Classifier: Programming Language :: Python :: 3.9
Classifier: Programming Language :: Python :: 3.10
Classifier: Programming Language :: Python :: 3.11
Requires-Dist: beautifulsoup4 (>=4.11.2,<5.0.0)
Requires-Dist: fake-useragent (>=1.1.1,<2.0.0)
Requires-Dist: matplotlib (>=3.7.1,<4.0.0)
Requires-Dist: pandas (>=1.5.3,<2.0.0)
Requires-Dist: python-decouple (>=3.8,<4.0)
Requires-Dist: selenium (>=4.8.2,<5.0.0)
Requires-Dist: webdriver-manager (>=3.8.5,<4.0.0)
